{
  "distribution" : {
    "5" : 1,
    "7" : 6,
    "8" : 8,
    "9" : 9,
    "10" : 20,
    "11" : 38,
    "12" : 63,
    "13" : 73,
    "14" : 84,
    "15" : 118,
    "16" : 113,
    "17" : 143,
    "18" : 149,
    "19" : 177,
    "20" : 184,
    "21" : 206,
    "22" : 203,
    "23" : 250,
    "24" : 231,
    "25" : 251,
    "26" : 258,
    "27" : 270,
    "28" : 295,
    "29" : 261,
    "30" : 280,
    "31" : 289,
    "32" : 246,
    "33" : 251,
    "34" : 250,
    "35" : 233,
    "36" : 232,
    "37" : 246,
    "38" : 220,
    "39" : 230,
    "40" : 210,
    "41" : 236,
    "42" : 192,
    "43" : 197,
    "44" : 185,
    "45" : 191,
    "46" : 181,
    "47" : 161,
    "48" : 180,
    "49" : 169,
    "50" : 142,
    "51" : 156,
    "52" : 162,
    "53" : 146,
    "54" : 138,
    "55" : 144,
    "56" : 121,
    "57" : 121,
    "58" : 124,
    "59" : 103,
    "60" : 119,
    "61" : 104,
    "62" : 83,
    "63" : 88,
    "64" : 80,
    "65" : 88,
    "66" : 66,
    "67" : 81,
    "68" : 65,
    "69" : 72,
    "70" : 60,
    "71" : 49,
    "72" : 54,
    "73" : 55,
    "74" : 59,
    "75" : 59,
    "76" : 52,
    "77" : 49,
    "78" : 53,
    "79" : 46,
    "80" : 49,
    "81" : 39,
    "82" : 41,
    "83" : 45,
    "84" : 35,
    "85" : 36,
    "86" : 27,
    "87" : 22,
    "88" : 32,
    "89" : 22,
    "90" : 31,
    "91" : 28,
    "92" : 29,
    "349" : 1,
    "93" : 20,
    "94" : 22,
    "95" : 24,
    "96" : 20,
    "97" : 26,
    "98" : 19,
    "99" : 14,
    "100" : 17,
    "101" : 20,
    "102" : 17,
    "103" : 18,
    "104" : 10,
    "105" : 5,
    "106" : 12,
    "107" : 11,
    "108" : 12,
    "109" : 10,
    "110" : 8,
    "111" : 11,
    "112" : 10,
    "113" : 10,
    "114" : 12,
    "115" : 2,
    "116" : 11,
    "117" : 12,
    "118" : 3,
    "119" : 6,
    "120" : 10,
    "121" : 10,
    "122" : 4,
    "123" : 8,
    "124" : 7,
    "125" : 11,
    "126" : 3,
    "127" : 5,
    "128" : 2,
    "129" : 7,
    "130" : 8,
    "131" : 5,
    "132" : 8,
    "133" : 6,
    "134" : 3,
    "135" : 3,
    "136" : 6,
    "137" : 2,
    "138" : 4,
    "139" : 6,
    "140" : 4,
    "141" : 3,
    "142" : 1,
    "143" : 2,
    "144" : 3,
    "145" : 2,
    "146" : 1,
    "149" : 1,
    "150" : 2,
    "151" : 2,
    "152" : 3,
    "154" : 2,
    "155" : 2,
    "156" : 1,
    "157" : 2,
    "158" : 1,
    "159" : 1,
    "160" : 2,
    "161" : 3,
    "162" : 1,
    "163" : 1,
    "164" : 1,
    "167" : 1,
    "170" : 2,
    "171" : 1,
    "172" : 1,
    "173" : 2,
    "174" : 1,
    "175" : 2,
    "185" : 1,
    "186" : 1,
    "188" : 1,
    "192" : 1,
    "193" : 1,
    "200" : 1,
    "201" : 1,
    "219" : 1,
    "221" : 1,
    "235" : 1
  },
  "mean" : 44.51247067002694,
  "stdDev" : 24.36178757683259
}