{
  "distribution" : {
    "7" : 1,
    "9" : 3,
    "10" : 2,
    "11" : 3,
    "12" : 16,
    "13" : 33,
    "14" : 41,
    "15" : 39,
    "16" : 53,
    "17" : 76,
    "18" : 102,
    "19" : 117,
    "20" : 127,
    "21" : 158,
    "22" : 170,
    "23" : 165,
    "24" : 165,
    "25" : 187,
    "26" : 217,
    "27" : 184,
    "28" : 200,
    "29" : 210,
    "30" : 242,
    "31" : 203,
    "32" : 241,
    "33" : 202,
    "34" : 246,
    "35" : 240,
    "36" : 226,
    "37" : 218,
    "38" : 238,
    "39" : 210,
    "40" : 234,
    "41" : 196,
    "42" : 236,
    "43" : 197,
    "44" : 200,
    "45" : 222,
    "46" : 191,
    "47" : 186,
    "48" : 190,
    "49" : 195,
    "50" : 172,
    "51" : 153,
    "52" : 180,
    "53" : 154,
    "54" : 157,
    "55" : 146,
    "56" : 158,
    "57" : 134,
    "58" : 147,
    "59" : 137,
    "60" : 149,
    "61" : 119,
    "62" : 118,
    "63" : 100,
    "64" : 113,
    "65" : 109,
    "66" : 119,
    "67" : 90,
    "68" : 103,
    "69" : 82,
    "70" : 77,
    "71" : 99,
    "72" : 91,
    "73" : 81,
    "74" : 76,
    "75" : 68,
    "76" : 74,
    "77" : 78,
    "78" : 59,
    "79" : 68,
    "80" : 67,
    "81" : 83,
    "82" : 64,
    "83" : 52,
    "84" : 59,
    "85" : 44,
    "86" : 67,
    "87" : 50,
    "88" : 49,
    "89" : 55,
    "90" : 46,
    "91" : 39,
    "92" : 39,
    "93" : 43,
    "94" : 34,
    "95" : 25,
    "96" : 25,
    "97" : 36,
    "98" : 38,
    "99" : 41,
    "100" : 24,
    "101" : 25,
    "102" : 20,
    "103" : 34,
    "104" : 26,
    "105" : 26,
    "106" : 28,
    "107" : 30,
    "108" : 30,
    "109" : 17,
    "110" : 16,
    "111" : 25,
    "112" : 22,
    "113" : 15,
    "114" : 20,
    "115" : 21,
    "116" : 19,
    "117" : 8,
    "118" : 14,
    "119" : 15,
    "120" : 9,
    "121" : 23,
    "122" : 15,
    "123" : 9,
    "124" : 12,
    "125" : 15,
    "126" : 12,
    "127" : 6,
    "128" : 12,
    "129" : 10,
    "130" : 10,
    "131" : 7,
    "132" : 8,
    "133" : 10,
    "134" : 7,
    "135" : 9,
    "136" : 7,
    "137" : 3,
    "138" : 15,
    "139" : 9,
    "140" : 3,
    "141" : 9,
    "142" : 9,
    "143" : 6,
    "144" : 6,
    "145" : 7,
    "146" : 8,
    "147" : 7,
    "148" : 6,
    "149" : 3,
    "150" : 5,
    "151" : 4,
    "152" : 5,
    "153" : 7,
    "154" : 5,
    "155" : 5,
    "156" : 3,
    "157" : 4,
    "158" : 5,
    "159" : 6,
    "160" : 1,
    "161" : 6,
    "162" : 3,
    "164" : 1,
    "165" : 1,
    "166" : 4,
    "167" : 1,
    "168" : 3,
    "169" : 2,
    "171" : 5,
    "172" : 4,
    "174" : 2,
    "175" : 2,
    "177" : 2,
    "178" : 1,
    "179" : 3,
    "180" : 1,
    "181" : 1,
    "182" : 1,
    "183" : 2,
    "185" : 2,
    "186" : 1,
    "187" : 1,
    "188" : 4,
    "189" : 1,
    "190" : 2,
    "191" : 2,
    "192" : 1,
    "193" : 1,
    "195" : 1,
    "196" : 2,
    "197" : 2,
    "198" : 2,
    "199" : 1,
    "200" : 1,
    "202" : 1,
    "205" : 2,
    "206" : 1,
    "208" : 1,
    "213" : 2,
    "218" : 1,
    "219" : 1,
    "224" : 1,
    "227" : 1,
    "232" : 2,
    "234" : 1,
    "238" : 1,
    "241" : 1,
    "242" : 1,
    "246" : 1,
    "264" : 1,
    "265" : 1,
    "281" : 1,
    "329" : 1
  },
  "mean" : 52.99059082817666,
  "stdDev" : 29.363768865253288
}