{
  "distribution" : {
    "13" : 4,
    "14" : 1,
    "15" : 3,
    "16" : 5,
    "17" : 9,
    "18" : 8,
    "19" : 15,
    "20" : 24,
    "21" : 30,
    "22" : 35,
    "23" : 35,
    "24" : 59,
    "25" : 56,
    "26" : 70,
    "27" : 67,
    "28" : 93,
    "29" : 76,
    "30" : 92,
    "31" : 97,
    "32" : 106,
    "33" : 122,
    "34" : 131,
    "35" : 125,
    "36" : 131,
    "37" : 153,
    "38" : 146,
    "39" : 146,
    "40" : 135,
    "41" : 115,
    "42" : 144,
    "43" : 138,
    "44" : 163,
    "45" : 146,
    "46" : 153,
    "47" : 158,
    "48" : 159,
    "49" : 149,
    "50" : 156,
    "51" : 160,
    "52" : 166,
    "53" : 151,
    "54" : 151,
    "55" : 142,
    "56" : 147,
    "57" : 181,
    "58" : 137,
    "59" : 153,
    "60" : 142,
    "61" : 157,
    "62" : 128,
    "63" : 140,
    "64" : 156,
    "65" : 161,
    "66" : 140,
    "67" : 119,
    "68" : 124,
    "69" : 134,
    "70" : 110,
    "71" : 110,
    "72" : 113,
    "73" : 103,
    "74" : 114,
    "75" : 116,
    "76" : 120,
    "77" : 95,
    "78" : 103,
    "79" : 106,
    "80" : 105,
    "81" : 88,
    "82" : 106,
    "83" : 112,
    "84" : 79,
    "85" : 81,
    "86" : 87,
    "87" : 108,
    "88" : 77,
    "89" : 82,
    "90" : 82,
    "91" : 82,
    "92" : 77,
    "93" : 63,
    "94" : 90,
    "95" : 85,
    "96" : 96,
    "97" : 57,
    "98" : 70,
    "99" : 66,
    "100" : 66,
    "101" : 70,
    "102" : 80,
    "103" : 60,
    "104" : 63,
    "105" : 44,
    "106" : 68,
    "107" : 51,
    "108" : 51,
    "109" : 54,
    "110" : 56,
    "111" : 57,
    "112" : 47,
    "113" : 44,
    "114" : 41,
    "115" : 52,
    "116" : 31,
    "117" : 41,
    "118" : 49,
    "119" : 36,
    "120" : 51,
    "121" : 37,
    "122" : 37,
    "123" : 38,
    "124" : 45,
    "125" : 24,
    "126" : 33,
    "127" : 31,
    "128" : 32,
    "129" : 38,
    "130" : 37,
    "131" : 37,
    "132" : 32,
    "133" : 25,
    "134" : 31,
    "135" : 28,
    "136" : 35,
    "137" : 32,
    "138" : 21,
    "139" : 22,
    "140" : 19,
    "141" : 26,
    "142" : 18,
    "143" : 18,
    "144" : 22,
    "145" : 27,
    "146" : 23,
    "147" : 22,
    "148" : 25,
    "149" : 15,
    "150" : 30,
    "151" : 23,
    "152" : 16,
    "153" : 21,
    "154" : 17,
    "155" : 14,
    "156" : 14,
    "157" : 23,
    "158" : 21,
    "159" : 13,
    "160" : 15,
    "161" : 9,
    "162" : 16,
    "163" : 11,
    "164" : 13,
    "165" : 10,
    "166" : 16,
    "167" : 8,
    "168" : 12,
    "169" : 13,
    "170" : 11,
    "171" : 8,
    "172" : 6,
    "173" : 7,
    "174" : 10,
    "175" : 9,
    "176" : 9,
    "177" : 7,
    "178" : 9,
    "179" : 8,
    "180" : 9,
    "181" : 8,
    "182" : 9,
    "183" : 5,
    "184" : 7,
    "185" : 7,
    "186" : 8,
    "187" : 3,
    "188" : 9,
    "189" : 8,
    "190" : 5,
    "191" : 7,
    "192" : 4,
    "193" : 3,
    "194" : 4,
    "195" : 8,
    "196" : 6,
    "197" : 4,
    "198" : 4,
    "199" : 2,
    "200" : 8,
    "201" : 5,
    "202" : 8,
    "203" : 4,
    "204" : 6,
    "205" : 5,
    "206" : 5,
    "207" : 1,
    "208" : 3,
    "209" : 8,
    "210" : 8,
    "211" : 3,
    "212" : 4,
    "213" : 1,
    "214" : 3,
    "215" : 4,
    "217" : 3,
    "218" : 1,
    "219" : 1,
    "220" : 1,
    "221" : 4,
    "222" : 3,
    "223" : 4,
    "224" : 5,
    "225" : 3,
    "226" : 2,
    "227" : 3,
    "228" : 1,
    "229" : 5,
    "230" : 7,
    "231" : 2,
    "232" : 5,
    "233" : 4,
    "234" : 5,
    "236" : 2,
    "237" : 3,
    "238" : 6,
    "239" : 4,
    "241" : 3,
    "242" : 4,
    "243" : 1,
    "245" : 2,
    "246" : 2,
    "247" : 2,
    "248" : 3,
    "249" : 3,
    "250" : 2,
    "252" : 1,
    "253" : 2,
    "254" : 3,
    "255" : 3,
    "256" : 2,
    "257" : 2,
    "259" : 2,
    "264" : 1,
    "265" : 2,
    "268" : 2,
    "269" : 2,
    "270" : 1,
    "271" : 1,
    "276" : 1,
    "277" : 1,
    "278" : 1,
    "279" : 1,
    "283" : 1,
    "287" : 1,
    "288" : 1,
    "290" : 1,
    "291" : 1,
    "292" : 1,
    "294" : 1,
    "295" : 1,
    "296" : 1,
    "297" : 1,
    "298" : 1,
    "299" : 1,
    "300" : 1,
    "303" : 1,
    "305" : 2,
    "307" : 1,
    "308" : 1,
    "311" : 2,
    "313" : 1,
    "314" : 1,
    "315" : 1,
    "317" : 1,
    "322" : 1,
    "326" : 3,
    "332" : 1,
    "338" : 1,
    "347" : 1,
    "348" : 1
  },
  "mean" : 77.09931740614334,
  "stdDev" : 42.5817579401127
}