{
  "distribution" : {
    "9" : 3,
    "10" : 3,
    "11" : 11,
    "12" : 19,
    "13" : 26,
    "14" : 49,
    "15" : 51,
    "16" : 69,
    "17" : 77,
    "18" : 92,
    "19" : 114,
    "20" : 142,
    "21" : 140,
    "22" : 135,
    "23" : 157,
    "24" : 182,
    "25" : 178,
    "26" : 178,
    "27" : 197,
    "28" : 205,
    "29" : 236,
    "30" : 227,
    "31" : 195,
    "32" : 226,
    "33" : 213,
    "34" : 237,
    "35" : 200,
    "36" : 194,
    "37" : 219,
    "38" : 217,
    "39" : 228,
    "40" : 204,
    "41" : 219,
    "42" : 204,
    "43" : 194,
    "44" : 185,
    "45" : 186,
    "46" : 213,
    "47" : 171,
    "48" : 195,
    "49" : 193,
    "50" : 188,
    "51" : 170,
    "52" : 157,
    "53" : 177,
    "54" : 171,
    "55" : 178,
    "56" : 151,
    "57" : 130,
    "58" : 146,
    "59" : 124,
    "60" : 144,
    "61" : 124,
    "62" : 116,
    "63" : 115,
    "64" : 123,
    "65" : 131,
    "66" : 109,
    "67" : 109,
    "68" : 100,
    "69" : 112,
    "70" : 80,
    "71" : 79,
    "72" : 86,
    "73" : 98,
    "74" : 88,
    "75" : 102,
    "76" : 83,
    "77" : 74,
    "78" : 81,
    "79" : 61,
    "80" : 62,
    "81" : 71,
    "82" : 81,
    "83" : 64,
    "84" : 76,
    "85" : 60,
    "86" : 57,
    "87" : 57,
    "88" : 59,
    "89" : 56,
    "90" : 58,
    "91" : 43,
    "92" : 55,
    "93" : 48,
    "94" : 35,
    "95" : 50,
    "96" : 34,
    "97" : 37,
    "98" : 38,
    "99" : 55,
    "100" : 40,
    "101" : 39,
    "102" : 32,
    "103" : 33,
    "104" : 25,
    "105" : 35,
    "106" : 29,
    "107" : 17,
    "108" : 31,
    "109" : 22,
    "110" : 32,
    "111" : 29,
    "112" : 17,
    "113" : 19,
    "114" : 34,
    "115" : 20,
    "116" : 30,
    "117" : 22,
    "118" : 12,
    "119" : 21,
    "120" : 15,
    "121" : 22,
    "122" : 18,
    "123" : 19,
    "124" : 15,
    "125" : 20,
    "126" : 10,
    "127" : 11,
    "128" : 16,
    "129" : 14,
    "130" : 9,
    "131" : 17,
    "132" : 10,
    "133" : 5,
    "134" : 11,
    "135" : 7,
    "136" : 15,
    "137" : 14,
    "138" : 8,
    "139" : 10,
    "140" : 7,
    "141" : 13,
    "142" : 9,
    "143" : 9,
    "144" : 6,
    "145" : 8,
    "146" : 14,
    "147" : 9,
    "148" : 2,
    "149" : 11,
    "150" : 5,
    "151" : 4,
    "152" : 9,
    "153" : 10,
    "154" : 11,
    "155" : 7,
    "156" : 5,
    "157" : 8,
    "158" : 5,
    "159" : 2,
    "160" : 3,
    "161" : 5,
    "162" : 4,
    "163" : 6,
    "164" : 2,
    "165" : 3,
    "166" : 4,
    "167" : 7,
    "168" : 2,
    "169" : 3,
    "170" : 1,
    "171" : 3,
    "172" : 3,
    "173" : 4,
    "174" : 5,
    "175" : 3,
    "176" : 5,
    "177" : 1,
    "178" : 1,
    "179" : 4,
    "180" : 1,
    "182" : 1,
    "183" : 3,
    "184" : 1,
    "186" : 3,
    "187" : 1,
    "188" : 5,
    "189" : 1,
    "191" : 3,
    "192" : 1,
    "193" : 2,
    "194" : 1,
    "196" : 1,
    "198" : 1,
    "199" : 1,
    "200" : 3,
    "201" : 1,
    "203" : 2,
    "204" : 2,
    "206" : 1,
    "209" : 1,
    "210" : 1,
    "211" : 1,
    "212" : 1,
    "219" : 1,
    "223" : 1,
    "224" : 1,
    "225" : 1,
    "230" : 1,
    "232" : 2,
    "236" : 1,
    "239" : 2,
    "241" : 1,
    "243" : 1,
    "246" : 1,
    "253" : 2,
    "262" : 1,
    "284" : 1
  },
  "mean" : 55.34500041081259,
  "stdDev" : 31.151038663273162
}