{
  "distribution" : {
    "7" : 2,
    "8" : 5,
    "9" : 9,
    "10" : 8,
    "11" : 13,
    "12" : 30,
    "13" : 42,
    "14" : 52,
    "15" : 74,
    "16" : 81,
    "17" : 124,
    "18" : 144,
    "19" : 147,
    "20" : 145,
    "21" : 193,
    "22" : 193,
    "23" : 197,
    "24" : 227,
    "25" : 220,
    "26" : 226,
    "27" : 250,
    "28" : 222,
    "29" : 221,
    "30" : 227,
    "31" : 245,
    "32" : 231,
    "33" : 264,
    "34" : 222,
    "35" : 262,
    "36" : 226,
    "37" : 239,
    "38" : 222,
    "39" : 216,
    "40" : 221,
    "41" : 220,
    "42" : 183,
    "43" : 249,
    "44" : 176,
    "45" : 199,
    "46" : 180,
    "47" : 214,
    "48" : 186,
    "49" : 162,
    "50" : 180,
    "51" : 152,
    "52" : 176,
    "53" : 142,
    "54" : 155,
    "55" : 148,
    "56" : 149,
    "57" : 147,
    "58" : 139,
    "59" : 121,
    "60" : 120,
    "61" : 129,
    "62" : 146,
    "63" : 107,
    "64" : 110,
    "65" : 116,
    "66" : 116,
    "67" : 119,
    "68" : 96,
    "69" : 88,
    "70" : 93,
    "71" : 89,
    "72" : 77,
    "73" : 76,
    "74" : 75,
    "75" : 65,
    "76" : 107,
    "77" : 70,
    "78" : 64,
    "79" : 61,
    "80" : 54,
    "81" : 49,
    "82" : 65,
    "83" : 62,
    "84" : 50,
    "85" : 62,
    "86" : 52,
    "87" : 61,
    "88" : 41,
    "89" : 37,
    "90" : 37,
    "91" : 45,
    "92" : 35,
    "93" : 38,
    "94" : 42,
    "95" : 31,
    "96" : 31,
    "97" : 38,
    "98" : 34,
    "99" : 35,
    "100" : 29,
    "101" : 25,
    "102" : 33,
    "103" : 31,
    "104" : 23,
    "105" : 22,
    "106" : 17,
    "107" : 24,
    "108" : 25,
    "109" : 25,
    "110" : 18,
    "111" : 20,
    "112" : 20,
    "113" : 30,
    "114" : 17,
    "115" : 12,
    "116" : 20,
    "117" : 19,
    "118" : 19,
    "119" : 20,
    "120" : 23,
    "121" : 15,
    "122" : 11,
    "123" : 9,
    "124" : 8,
    "125" : 9,
    "126" : 13,
    "127" : 7,
    "128" : 22,
    "129" : 15,
    "130" : 7,
    "131" : 11,
    "132" : 7,
    "133" : 9,
    "134" : 7,
    "135" : 10,
    "136" : 6,
    "137" : 5,
    "138" : 8,
    "139" : 6,
    "140" : 10,
    "141" : 5,
    "142" : 4,
    "143" : 2,
    "144" : 5,
    "145" : 10,
    "146" : 8,
    "147" : 9,
    "148" : 8,
    "149" : 7,
    "150" : 5,
    "151" : 6,
    "152" : 3,
    "153" : 2,
    "154" : 3,
    "155" : 3,
    "156" : 4,
    "157" : 3,
    "158" : 3,
    "159" : 2,
    "160" : 5,
    "161" : 4,
    "162" : 3,
    "163" : 3,
    "164" : 3,
    "165" : 1,
    "166" : 4,
    "167" : 4,
    "169" : 2,
    "170" : 2,
    "171" : 1,
    "173" : 2,
    "175" : 1,
    "176" : 3,
    "177" : 2,
    "178" : 1,
    "179" : 3,
    "180" : 2,
    "182" : 1,
    "183" : 1,
    "184" : 2,
    "185" : 1,
    "186" : 2,
    "187" : 2,
    "190" : 2,
    "194" : 2,
    "195" : 1,
    "196" : 2,
    "197" : 1,
    "199" : 1,
    "200" : 3,
    "203" : 1,
    "207" : 2,
    "209" : 2,
    "220" : 1,
    "223" : 1,
    "227" : 1,
    "231" : 1,
    "232" : 2,
    "233" : 1,
    "239" : 1,
    "240" : 1,
    "241" : 1,
    "251" : 1,
    "254" : 1,
    "291" : 1
  },
  "mean" : 51.20226812474686,
  "stdDev" : 29.025646715390142
}