{
  "distribution" : {
    "4" : 2,
    "5" : 3,
    "6" : 10,
    "7" : 18,
    "8" : 61,
    "9" : 95,
    "10" : 100,
    "11" : 166,
    "12" : 196,
    "13" : 241,
    "14" : 254,
    "15" : 278,
    "16" : 310,
    "17" : 333,
    "18" : 363,
    "19" : 333,
    "20" : 382,
    "21" : 371,
    "22" : 381,
    "23" : 380,
    "24" : 338,
    "25" : 356,
    "26" : 341,
    "27" : 325,
    "28" : 327,
    "29" : 328,
    "30" : 352,
    "31" : 285,
    "32" : 303,
    "33" : 255,
    "34" : 295,
    "35" : 259,
    "36" : 232,
    "37" : 228,
    "38" : 238,
    "39" : 216,
    "40" : 200,
    "41" : 176,
    "42" : 158,
    "43" : 166,
    "44" : 155,
    "45" : 147,
    "46" : 158,
    "47" : 137,
    "48" : 127,
    "49" : 130,
    "50" : 118,
    "51" : 102,
    "52" : 97,
    "53" : 101,
    "54" : 99,
    "55" : 94,
    "56" : 74,
    "57" : 78,
    "58" : 72,
    "59" : 89,
    "60" : 82,
    "61" : 63,
    "62" : 58,
    "63" : 61,
    "64" : 56,
    "65" : 55,
    "66" : 62,
    "67" : 55,
    "68" : 54,
    "69" : 54,
    "70" : 41,
    "71" : 38,
    "72" : 35,
    "73" : 37,
    "74" : 39,
    "75" : 30,
    "76" : 39,
    "77" : 34,
    "78" : 29,
    "79" : 25,
    "80" : 24,
    "81" : 24,
    "82" : 21,
    "83" : 21,
    "84" : 21,
    "85" : 31,
    "86" : 21,
    "87" : 17,
    "88" : 20,
    "89" : 10,
    "90" : 13,
    "91" : 6,
    "92" : 20,
    "93" : 13,
    "94" : 7,
    "95" : 12,
    "96" : 18,
    "97" : 14,
    "98" : 9,
    "99" : 8,
    "100" : 11,
    "101" : 7,
    "102" : 7,
    "103" : 7,
    "104" : 7,
    "105" : 5,
    "106" : 8,
    "107" : 7,
    "108" : 3,
    "109" : 7,
    "110" : 6,
    "111" : 4,
    "112" : 2,
    "113" : 4,
    "114" : 6,
    "115" : 2,
    "116" : 8,
    "117" : 4,
    "118" : 2,
    "119" : 3,
    "120" : 3,
    "121" : 7,
    "122" : 3,
    "123" : 3,
    "124" : 3,
    "125" : 2,
    "127" : 2,
    "128" : 1,
    "129" : 3,
    "130" : 3,
    "131" : 1,
    "132" : 1,
    "134" : 1,
    "135" : 2,
    "136" : 3,
    "137" : 1,
    "138" : 1,
    "139" : 1,
    "141" : 1,
    "144" : 2,
    "145" : 1,
    "146" : 1,
    "149" : 2,
    "150" : 1,
    "151" : 1,
    "152" : 1,
    "155" : 1,
    "159" : 1,
    "168" : 1,
    "170" : 1,
    "173" : 1,
    "209" : 1
  },
  "mean" : 34.88988118350547,
  "stdDev" : 20.19933640806945
}