{
  "distribution" : {
    "6" : 1,
    "8" : 1,
    "9" : 7,
    "10" : 6,
    "11" : 9,
    "12" : 22,
    "13" : 28,
    "14" : 23,
    "15" : 52,
    "16" : 52,
    "17" : 60,
    "18" : 87,
    "19" : 101,
    "20" : 92,
    "21" : 115,
    "22" : 159,
    "23" : 154,
    "24" : 179,
    "25" : 165,
    "26" : 174,
    "27" : 187,
    "28" : 198,
    "29" : 215,
    "30" : 214,
    "31" : 191,
    "32" : 235,
    "33" : 206,
    "34" : 223,
    "35" : 223,
    "36" : 202,
    "37" : 228,
    "38" : 215,
    "39" : 218,
    "40" : 224,
    "41" : 210,
    "42" : 187,
    "43" : 217,
    "44" : 196,
    "45" : 180,
    "46" : 184,
    "47" : 188,
    "48" : 173,
    "49" : 167,
    "50" : 183,
    "51" : 165,
    "52" : 176,
    "53" : 170,
    "54" : 175,
    "55" : 159,
    "56" : 140,
    "57" : 169,
    "58" : 133,
    "59" : 147,
    "60" : 128,
    "61" : 111,
    "62" : 140,
    "63" : 126,
    "64" : 114,
    "65" : 113,
    "66" : 109,
    "67" : 97,
    "68" : 111,
    "69" : 120,
    "70" : 97,
    "71" : 100,
    "72" : 105,
    "73" : 82,
    "74" : 88,
    "75" : 70,
    "76" : 79,
    "77" : 88,
    "78" : 81,
    "79" : 63,
    "80" : 92,
    "81" : 72,
    "82" : 79,
    "83" : 66,
    "84" : 56,
    "85" : 61,
    "86" : 52,
    "87" : 72,
    "88" : 59,
    "89" : 56,
    "90" : 47,
    "91" : 39,
    "92" : 57,
    "93" : 45,
    "94" : 47,
    "95" : 67,
    "96" : 49,
    "97" : 51,
    "98" : 45,
    "99" : 46,
    "100" : 36,
    "101" : 47,
    "102" : 34,
    "103" : 27,
    "104" : 33,
    "105" : 31,
    "106" : 44,
    "107" : 24,
    "108" : 24,
    "109" : 29,
    "110" : 25,
    "111" : 29,
    "112" : 26,
    "113" : 21,
    "114" : 26,
    "115" : 11,
    "116" : 22,
    "117" : 19,
    "118" : 23,
    "119" : 15,
    "120" : 21,
    "121" : 17,
    "122" : 15,
    "123" : 23,
    "124" : 16,
    "125" : 15,
    "126" : 13,
    "127" : 18,
    "128" : 11,
    "129" : 17,
    "130" : 15,
    "131" : 14,
    "132" : 9,
    "133" : 13,
    "134" : 12,
    "135" : 9,
    "136" : 5,
    "137" : 10,
    "138" : 12,
    "139" : 10,
    "140" : 13,
    "141" : 13,
    "142" : 8,
    "143" : 15,
    "144" : 6,
    "145" : 6,
    "146" : 6,
    "147" : 6,
    "148" : 10,
    "149" : 5,
    "150" : 4,
    "151" : 11,
    "152" : 8,
    "153" : 3,
    "154" : 5,
    "155" : 6,
    "156" : 6,
    "157" : 3,
    "158" : 7,
    "159" : 5,
    "160" : 5,
    "161" : 4,
    "162" : 6,
    "163" : 8,
    "164" : 3,
    "165" : 3,
    "166" : 3,
    "167" : 3,
    "168" : 3,
    "169" : 4,
    "170" : 1,
    "171" : 5,
    "172" : 2,
    "173" : 3,
    "174" : 5,
    "176" : 5,
    "177" : 1,
    "178" : 3,
    "179" : 1,
    "182" : 2,
    "183" : 1,
    "184" : 1,
    "185" : 3,
    "186" : 3,
    "187" : 3,
    "188" : 5,
    "189" : 2,
    "190" : 2,
    "191" : 1,
    "192" : 1,
    "193" : 2,
    "194" : 2,
    "196" : 1,
    "197" : 3,
    "201" : 3,
    "202" : 1,
    "203" : 1,
    "204" : 3,
    "205" : 1,
    "206" : 1,
    "207" : 4,
    "208" : 1,
    "209" : 2,
    "210" : 1,
    "213" : 1,
    "214" : 2,
    "215" : 1,
    "217" : 1,
    "218" : 2,
    "219" : 1,
    "220" : 2,
    "222" : 1,
    "223" : 1,
    "224" : 2,
    "229" : 1,
    "234" : 1,
    "238" : 1,
    "239" : 2,
    "268" : 1,
    "269" : 1,
    "273" : 1,
    "283" : 2
  },
  "mean" : 56.28093423886036,
  "stdDev" : 31.552224487800117
}