{
  "distribution" : {
    "10" : 2,
    "11" : 7,
    "12" : 8,
    "13" : 15,
    "14" : 8,
    "15" : 30,
    "16" : 51,
    "17" : 42,
    "18" : 66,
    "19" : 65,
    "20" : 83,
    "21" : 102,
    "22" : 107,
    "23" : 104,
    "24" : 130,
    "25" : 166,
    "26" : 143,
    "27" : 163,
    "28" : 182,
    "29" : 167,
    "30" : 175,
    "31" : 186,
    "32" : 169,
    "33" : 195,
    "34" : 201,
    "35" : 170,
    "36" : 207,
    "37" : 214,
    "38" : 190,
    "39" : 220,
    "40" : 231,
    "41" : 192,
    "42" : 209,
    "43" : 210,
    "44" : 193,
    "45" : 184,
    "46" : 164,
    "47" : 173,
    "48" : 176,
    "49" : 196,
    "50" : 201,
    "51" : 133,
    "52" : 155,
    "53" : 160,
    "54" : 138,
    "55" : 170,
    "56" : 185,
    "57" : 164,
    "58" : 139,
    "59" : 150,
    "60" : 134,
    "61" : 136,
    "62" : 120,
    "63" : 116,
    "64" : 145,
    "65" : 125,
    "66" : 128,
    "67" : 111,
    "68" : 117,
    "69" : 100,
    "70" : 109,
    "71" : 108,
    "72" : 101,
    "73" : 107,
    "74" : 92,
    "75" : 88,
    "76" : 86,
    "77" : 89,
    "78" : 101,
    "79" : 77,
    "80" : 82,
    "81" : 78,
    "82" : 85,
    "83" : 93,
    "84" : 81,
    "85" : 63,
    "86" : 69,
    "87" : 76,
    "88" : 62,
    "89" : 46,
    "90" : 57,
    "91" : 61,
    "92" : 58,
    "93" : 71,
    "94" : 43,
    "95" : 47,
    "96" : 54,
    "97" : 47,
    "98" : 55,
    "99" : 55,
    "100" : 54,
    "101" : 48,
    "102" : 56,
    "103" : 40,
    "104" : 37,
    "105" : 26,
    "106" : 43,
    "107" : 44,
    "108" : 19,
    "109" : 32,
    "110" : 34,
    "111" : 24,
    "112" : 42,
    "113" : 36,
    "114" : 34,
    "115" : 32,
    "116" : 16,
    "117" : 19,
    "118" : 24,
    "119" : 19,
    "120" : 31,
    "121" : 23,
    "122" : 22,
    "123" : 20,
    "124" : 15,
    "125" : 24,
    "126" : 24,
    "127" : 26,
    "128" : 22,
    "129" : 25,
    "130" : 17,
    "131" : 14,
    "132" : 25,
    "133" : 15,
    "134" : 14,
    "135" : 13,
    "136" : 21,
    "137" : 16,
    "138" : 14,
    "139" : 13,
    "140" : 20,
    "141" : 15,
    "142" : 14,
    "143" : 14,
    "144" : 9,
    "145" : 16,
    "146" : 12,
    "147" : 15,
    "148" : 10,
    "149" : 9,
    "150" : 12,
    "151" : 13,
    "152" : 9,
    "153" : 3,
    "154" : 11,
    "155" : 5,
    "156" : 8,
    "157" : 11,
    "158" : 10,
    "159" : 6,
    "160" : 4,
    "161" : 6,
    "162" : 8,
    "163" : 2,
    "164" : 2,
    "165" : 6,
    "166" : 11,
    "167" : 4,
    "168" : 6,
    "169" : 6,
    "170" : 6,
    "171" : 4,
    "172" : 7,
    "173" : 6,
    "174" : 5,
    "175" : 2,
    "177" : 6,
    "178" : 1,
    "179" : 3,
    "180" : 2,
    "181" : 5,
    "182" : 5,
    "183" : 4,
    "185" : 5,
    "186" : 3,
    "188" : 5,
    "189" : 1,
    "190" : 1,
    "191" : 4,
    "192" : 1,
    "194" : 2,
    "195" : 2,
    "196" : 1,
    "197" : 2,
    "198" : 2,
    "199" : 2,
    "200" : 1,
    "201" : 2,
    "202" : 2,
    "205" : 4,
    "206" : 4,
    "207" : 4,
    "209" : 1,
    "210" : 1,
    "211" : 1,
    "213" : 3,
    "214" : 1,
    "215" : 1,
    "216" : 2,
    "218" : 2,
    "219" : 2,
    "220" : 1,
    "222" : 1,
    "223" : 2,
    "224" : 2,
    "225" : 1,
    "226" : 2,
    "228" : 1,
    "229" : 1,
    "230" : 1,
    "232" : 1,
    "233" : 1,
    "236" : 1,
    "238" : 1,
    "239" : 2,
    "241" : 2,
    "243" : 1,
    "244" : 1,
    "245" : 1,
    "247" : 1,
    "248" : 1,
    "250" : 1,
    "251" : 1,
    "261" : 1,
    "289" : 1,
    "292" : 1,
    "308" : 1,
    "309" : 1
  },
  "mean" : 61.14622015915119,
  "stdDev" : 34.26455445868631
}