{
  "distribution" : {
    "7" : 1,
    "8" : 3,
    "9" : 5,
    "10" : 7,
    "11" : 23,
    "12" : 26,
    "13" : 54,
    "14" : 49,
    "15" : 60,
    "16" : 97,
    "17" : 113,
    "18" : 120,
    "19" : 129,
    "20" : 148,
    "21" : 164,
    "22" : 173,
    "23" : 214,
    "24" : 204,
    "25" : 197,
    "26" : 216,
    "27" : 211,
    "28" : 238,
    "29" : 233,
    "30" : 249,
    "31" : 233,
    "32" : 256,
    "33" : 254,
    "34" : 219,
    "35" : 239,
    "36" : 244,
    "37" : 191,
    "38" : 240,
    "39" : 222,
    "40" : 226,
    "41" : 180,
    "42" : 218,
    "43" : 201,
    "44" : 203,
    "45" : 230,
    "46" : 198,
    "47" : 166,
    "48" : 208,
    "49" : 184,
    "50" : 164,
    "51" : 181,
    "52" : 161,
    "53" : 167,
    "54" : 160,
    "55" : 140,
    "56" : 125,
    "57" : 142,
    "58" : 139,
    "59" : 127,
    "60" : 120,
    "61" : 111,
    "62" : 115,
    "63" : 126,
    "64" : 115,
    "65" : 116,
    "66" : 120,
    "67" : 90,
    "68" : 92,
    "69" : 95,
    "70" : 93,
    "71" : 86,
    "72" : 72,
    "73" : 87,
    "74" : 85,
    "75" : 80,
    "76" : 83,
    "77" : 67,
    "78" : 64,
    "79" : 65,
    "80" : 55,
    "81" : 53,
    "82" : 64,
    "83" : 57,
    "84" : 46,
    "85" : 54,
    "86" : 54,
    "87" : 56,
    "88" : 46,
    "89" : 42,
    "90" : 43,
    "91" : 41,
    "92" : 34,
    "93" : 36,
    "94" : 41,
    "95" : 33,
    "96" : 37,
    "97" : 35,
    "98" : 34,
    "99" : 24,
    "100" : 21,
    "101" : 36,
    "102" : 24,
    "103" : 21,
    "104" : 25,
    "105" : 32,
    "106" : 16,
    "107" : 25,
    "108" : 17,
    "109" : 25,
    "110" : 16,
    "111" : 22,
    "112" : 20,
    "113" : 23,
    "114" : 21,
    "115" : 15,
    "116" : 19,
    "117" : 21,
    "118" : 18,
    "119" : 14,
    "120" : 12,
    "121" : 14,
    "122" : 12,
    "123" : 15,
    "124" : 12,
    "125" : 15,
    "126" : 7,
    "127" : 8,
    "128" : 7,
    "129" : 10,
    "130" : 10,
    "131" : 11,
    "132" : 12,
    "133" : 10,
    "134" : 13,
    "135" : 8,
    "136" : 8,
    "137" : 5,
    "138" : 8,
    "139" : 6,
    "140" : 7,
    "141" : 7,
    "142" : 4,
    "143" : 6,
    "144" : 7,
    "145" : 2,
    "146" : 8,
    "147" : 5,
    "148" : 2,
    "149" : 6,
    "150" : 3,
    "151" : 9,
    "152" : 4,
    "153" : 5,
    "154" : 5,
    "155" : 5,
    "156" : 2,
    "157" : 4,
    "158" : 4,
    "159" : 7,
    "160" : 5,
    "161" : 1,
    "163" : 2,
    "164" : 2,
    "165" : 1,
    "166" : 2,
    "167" : 3,
    "171" : 3,
    "172" : 2,
    "173" : 4,
    "174" : 3,
    "175" : 1,
    "176" : 3,
    "177" : 1,
    "178" : 5,
    "180" : 4,
    "181" : 1,
    "182" : 1,
    "183" : 1,
    "184" : 1,
    "186" : 3,
    "188" : 1,
    "189" : 1,
    "190" : 3,
    "191" : 2,
    "192" : 2,
    "194" : 1,
    "196" : 1,
    "199" : 1,
    "203" : 1,
    "204" : 1,
    "205" : 1,
    "206" : 4,
    "210" : 2,
    "212" : 1,
    "219" : 1,
    "220" : 1,
    "221" : 1,
    "223" : 2,
    "224" : 1,
    "231" : 1,
    "239" : 1,
    "246" : 2
  },
  "mean" : 51.30710283454186,
  "stdDev" : 28.837944873071674
}