{
  "distribution" : {
    "7" : 1,
    "8" : 2,
    "9" : 4,
    "10" : 9,
    "11" : 14,
    "12" : 43,
    "13" : 41,
    "14" : 46,
    "15" : 80,
    "16" : 76,
    "17" : 99,
    "18" : 132,
    "19" : 128,
    "20" : 165,
    "21" : 165,
    "22" : 174,
    "23" : 177,
    "24" : 223,
    "25" : 195,
    "26" : 208,
    "27" : 233,
    "28" : 258,
    "29" : 240,
    "30" : 261,
    "31" : 268,
    "32" : 239,
    "33" : 265,
    "34" : 259,
    "35" : 253,
    "36" : 243,
    "37" : 260,
    "38" : 254,
    "39" : 232,
    "40" : 235,
    "41" : 240,
    "42" : 243,
    "43" : 204,
    "44" : 226,
    "45" : 181,
    "46" : 193,
    "47" : 191,
    "48" : 185,
    "49" : 173,
    "50" : 175,
    "51" : 144,
    "52" : 154,
    "53" : 175,
    "54" : 150,
    "55" : 138,
    "56" : 130,
    "57" : 138,
    "58" : 124,
    "59" : 139,
    "60" : 134,
    "61" : 136,
    "62" : 116,
    "63" : 108,
    "64" : 111,
    "65" : 111,
    "66" : 111,
    "67" : 117,
    "68" : 92,
    "69" : 93,
    "70" : 73,
    "71" : 92,
    "72" : 90,
    "73" : 81,
    "74" : 95,
    "75" : 75,
    "76" : 70,
    "77" : 78,
    "78" : 60,
    "79" : 61,
    "80" : 68,
    "81" : 68,
    "82" : 51,
    "83" : 56,
    "84" : 52,
    "85" : 53,
    "86" : 63,
    "87" : 49,
    "88" : 41,
    "89" : 44,
    "90" : 49,
    "91" : 47,
    "92" : 39,
    "93" : 22,
    "94" : 39,
    "95" : 37,
    "96" : 35,
    "97" : 31,
    "98" : 26,
    "99" : 37,
    "100" : 33,
    "101" : 26,
    "102" : 30,
    "103" : 23,
    "104" : 29,
    "105" : 20,
    "106" : 19,
    "107" : 24,
    "108" : 21,
    "109" : 17,
    "110" : 29,
    "111" : 27,
    "112" : 25,
    "113" : 15,
    "114" : 17,
    "115" : 19,
    "116" : 10,
    "117" : 16,
    "118" : 18,
    "119" : 18,
    "120" : 17,
    "121" : 14,
    "122" : 11,
    "123" : 12,
    "124" : 7,
    "125" : 13,
    "126" : 13,
    "127" : 15,
    "128" : 15,
    "129" : 17,
    "130" : 11,
    "131" : 9,
    "132" : 10,
    "133" : 7,
    "134" : 10,
    "135" : 12,
    "136" : 10,
    "137" : 11,
    "138" : 5,
    "139" : 13,
    "140" : 12,
    "141" : 10,
    "142" : 9,
    "143" : 8,
    "144" : 13,
    "145" : 5,
    "146" : 8,
    "147" : 4,
    "148" : 1,
    "149" : 10,
    "150" : 5,
    "151" : 4,
    "152" : 8,
    "153" : 3,
    "154" : 5,
    "155" : 6,
    "156" : 1,
    "157" : 2,
    "158" : 5,
    "160" : 5,
    "161" : 4,
    "162" : 1,
    "163" : 3,
    "164" : 2,
    "165" : 1,
    "166" : 2,
    "167" : 5,
    "168" : 2,
    "169" : 3,
    "170" : 5,
    "171" : 1,
    "172" : 4,
    "173" : 3,
    "175" : 4,
    "176" : 2,
    "177" : 4,
    "178" : 1,
    "179" : 4,
    "180" : 2,
    "182" : 2,
    "183" : 1,
    "184" : 1,
    "186" : 2,
    "188" : 1,
    "190" : 2,
    "192" : 1,
    "193" : 1,
    "194" : 2,
    "195" : 3,
    "197" : 3,
    "198" : 1,
    "199" : 2,
    "200" : 1,
    "201" : 1,
    "207" : 1,
    "208" : 1,
    "210" : 1,
    "211" : 1,
    "218" : 1,
    "219" : 1,
    "231" : 1,
    "232" : 1,
    "236" : 1,
    "238" : 2,
    "239" : 1,
    "244" : 1,
    "266" : 1,
    "270" : 1
  },
  "mean" : 51.48878205128205,
  "stdDev" : 29.34639720455486
}