{
  "distribution" : {
    "6" : 1,
    "9" : 4,
    "10" : 4,
    "11" : 15,
    "12" : 18,
    "13" : 23,
    "14" : 43,
    "15" : 42,
    "16" : 61,
    "17" : 68,
    "18" : 96,
    "19" : 94,
    "20" : 123,
    "21" : 123,
    "22" : 165,
    "23" : 170,
    "24" : 161,
    "25" : 189,
    "26" : 184,
    "27" : 209,
    "28" : 223,
    "29" : 203,
    "30" : 216,
    "31" : 214,
    "32" : 232,
    "33" : 259,
    "34" : 209,
    "35" : 193,
    "36" : 233,
    "37" : 203,
    "38" : 217,
    "39" : 214,
    "40" : 224,
    "41" : 186,
    "42" : 215,
    "43" : 219,
    "44" : 238,
    "45" : 193,
    "46" : 213,
    "47" : 196,
    "48" : 207,
    "49" : 192,
    "50" : 171,
    "51" : 183,
    "52" : 161,
    "53" : 161,
    "54" : 194,
    "55" : 164,
    "56" : 139,
    "57" : 173,
    "58" : 148,
    "59" : 133,
    "60" : 132,
    "61" : 125,
    "62" : 161,
    "63" : 120,
    "64" : 128,
    "65" : 134,
    "66" : 121,
    "67" : 99,
    "68" : 100,
    "69" : 99,
    "70" : 96,
    "71" : 101,
    "72" : 100,
    "73" : 111,
    "74" : 82,
    "75" : 77,
    "76" : 83,
    "77" : 84,
    "78" : 72,
    "79" : 69,
    "80" : 72,
    "81" : 68,
    "82" : 72,
    "83" : 59,
    "84" : 51,
    "85" : 66,
    "86" : 64,
    "87" : 63,
    "88" : 64,
    "89" : 54,
    "90" : 51,
    "91" : 42,
    "92" : 55,
    "93" : 40,
    "94" : 39,
    "95" : 35,
    "96" : 40,
    "97" : 39,
    "98" : 28,
    "99" : 42,
    "100" : 45,
    "101" : 39,
    "102" : 33,
    "103" : 37,
    "104" : 33,
    "105" : 35,
    "106" : 23,
    "107" : 28,
    "108" : 25,
    "109" : 35,
    "110" : 41,
    "111" : 21,
    "112" : 15,
    "113" : 15,
    "114" : 23,
    "115" : 17,
    "116" : 22,
    "117" : 18,
    "118" : 29,
    "119" : 23,
    "120" : 22,
    "121" : 20,
    "122" : 14,
    "123" : 14,
    "124" : 16,
    "125" : 11,
    "126" : 13,
    "127" : 23,
    "128" : 7,
    "129" : 7,
    "130" : 5,
    "131" : 15,
    "132" : 12,
    "133" : 11,
    "134" : 13,
    "135" : 16,
    "136" : 6,
    "137" : 8,
    "138" : 14,
    "139" : 6,
    "140" : 9,
    "141" : 7,
    "142" : 8,
    "143" : 9,
    "144" : 9,
    "145" : 4,
    "146" : 7,
    "147" : 14,
    "148" : 6,
    "149" : 5,
    "150" : 8,
    "151" : 9,
    "152" : 4,
    "153" : 2,
    "154" : 6,
    "155" : 8,
    "156" : 3,
    "157" : 5,
    "158" : 9,
    "159" : 8,
    "160" : 5,
    "161" : 2,
    "162" : 8,
    "163" : 3,
    "164" : 6,
    "165" : 5,
    "166" : 3,
    "167" : 7,
    "168" : 7,
    "169" : 3,
    "170" : 2,
    "171" : 4,
    "172" : 3,
    "173" : 3,
    "174" : 1,
    "175" : 4,
    "176" : 6,
    "177" : 5,
    "178" : 2,
    "179" : 4,
    "180" : 3,
    "182" : 1,
    "183" : 5,
    "184" : 2,
    "186" : 4,
    "187" : 4,
    "188" : 3,
    "189" : 5,
    "190" : 1,
    "191" : 1,
    "193" : 2,
    "194" : 4,
    "195" : 4,
    "196" : 1,
    "197" : 1,
    "198" : 2,
    "200" : 1,
    "201" : 2,
    "202" : 2,
    "203" : 1,
    "204" : 2,
    "205" : 1,
    "206" : 2,
    "207" : 1,
    "209" : 1,
    "210" : 1,
    "211" : 4,
    "212" : 1,
    "215" : 1,
    "216" : 1,
    "219" : 2,
    "222" : 1,
    "229" : 1,
    "232" : 1,
    "234" : 2,
    "235" : 1,
    "237" : 1,
    "238" : 1,
    "241" : 2,
    "249" : 1,
    "255" : 1,
    "256" : 2,
    "265" : 1,
    "299" : 1
  },
  "mean" : 55.55577109602328,
  "stdDev" : 31.52824308764024
}