{
  "distribution" : {
    "8" : 2,
    "9" : 6,
    "10" : 9,
    "11" : 16,
    "12" : 22,
    "13" : 36,
    "14" : 49,
    "15" : 49,
    "16" : 80,
    "17" : 90,
    "18" : 118,
    "19" : 143,
    "20" : 142,
    "21" : 152,
    "22" : 170,
    "23" : 170,
    "24" : 178,
    "25" : 215,
    "26" : 212,
    "27" : 235,
    "28" : 210,
    "29" : 244,
    "30" : 235,
    "31" : 218,
    "32" : 230,
    "33" : 227,
    "34" : 253,
    "35" : 237,
    "36" : 243,
    "37" : 241,
    "38" : 211,
    "39" : 225,
    "40" : 229,
    "41" : 212,
    "42" : 221,
    "43" : 214,
    "44" : 211,
    "45" : 193,
    "46" : 189,
    "47" : 204,
    "48" : 181,
    "49" : 187,
    "50" : 187,
    "51" : 162,
    "52" : 162,
    "53" : 183,
    "54" : 151,
    "55" : 155,
    "56" : 148,
    "57" : 143,
    "58" : 132,
    "59" : 145,
    "60" : 117,
    "61" : 136,
    "62" : 122,
    "63" : 122,
    "64" : 118,
    "65" : 110,
    "66" : 106,
    "67" : 105,
    "68" : 110,
    "69" : 93,
    "70" : 117,
    "71" : 75,
    "72" : 85,
    "73" : 81,
    "74" : 85,
    "75" : 88,
    "76" : 81,
    "77" : 75,
    "78" : 56,
    "79" : 79,
    "80" : 65,
    "81" : 71,
    "82" : 65,
    "83" : 65,
    "84" : 53,
    "85" : 48,
    "86" : 56,
    "87" : 48,
    "88" : 41,
    "89" : 40,
    "90" : 51,
    "91" : 41,
    "92" : 52,
    "93" : 41,
    "94" : 42,
    "95" : 39,
    "96" : 42,
    "97" : 40,
    "98" : 30,
    "99" : 34,
    "100" : 46,
    "101" : 33,
    "102" : 34,
    "103" : 24,
    "104" : 18,
    "105" : 28,
    "106" : 29,
    "107" : 33,
    "108" : 15,
    "109" : 34,
    "110" : 27,
    "111" : 21,
    "112" : 34,
    "113" : 25,
    "114" : 16,
    "115" : 14,
    "116" : 16,
    "117" : 19,
    "118" : 12,
    "119" : 16,
    "120" : 15,
    "121" : 13,
    "122" : 15,
    "123" : 15,
    "124" : 11,
    "125" : 14,
    "126" : 8,
    "127" : 15,
    "128" : 11,
    "129" : 12,
    "130" : 12,
    "131" : 9,
    "132" : 5,
    "133" : 10,
    "134" : 11,
    "135" : 6,
    "136" : 17,
    "137" : 7,
    "138" : 13,
    "139" : 9,
    "140" : 7,
    "141" : 4,
    "142" : 5,
    "143" : 12,
    "144" : 7,
    "145" : 7,
    "146" : 12,
    "147" : 3,
    "148" : 4,
    "149" : 5,
    "150" : 6,
    "151" : 6,
    "152" : 3,
    "153" : 7,
    "154" : 5,
    "155" : 6,
    "156" : 3,
    "157" : 2,
    "158" : 5,
    "159" : 3,
    "160" : 6,
    "161" : 4,
    "163" : 6,
    "164" : 6,
    "165" : 4,
    "166" : 5,
    "167" : 7,
    "168" : 6,
    "169" : 2,
    "170" : 3,
    "171" : 1,
    "172" : 3,
    "173" : 3,
    "174" : 2,
    "175" : 3,
    "176" : 2,
    "178" : 1,
    "179" : 1,
    "181" : 1,
    "182" : 4,
    "183" : 2,
    "184" : 5,
    "185" : 1,
    "187" : 1,
    "189" : 2,
    "190" : 2,
    "193" : 2,
    "194" : 1,
    "195" : 1,
    "196" : 3,
    "197" : 1,
    "199" : 3,
    "200" : 1,
    "202" : 1,
    "203" : 1,
    "204" : 1,
    "205" : 2,
    "207" : 1,
    "208" : 1,
    "210" : 1,
    "211" : 1,
    "212" : 1,
    "218" : 1,
    "219" : 1,
    "222" : 1,
    "225" : 1,
    "230" : 1,
    "231" : 1,
    "239" : 1,
    "241" : 1,
    "242" : 1,
    "243" : 1,
    "250" : 1,
    "252" : 1,
    "256" : 1,
    "265" : 1,
    "269" : 1
  },
  "mean" : 52.986160569763676,
  "stdDev" : 30.04883470780926
}