{
  "distribution" : {
    "6" : 1,
    "9" : 4,
    "10" : 10,
    "267" : 1,
    "11" : 21,
    "12" : 29,
    "13" : 42,
    "14" : 55,
    "15" : 69,
    "16" : 83,
    "17" : 126,
    "18" : 113,
    "19" : 124,
    "20" : 158,
    "21" : 184,
    "22" : 215,
    "23" : 203,
    "24" : 238,
    "25" : 214,
    "26" : 210,
    "27" : 223,
    "28" : 238,
    "29" : 227,
    "30" : 248,
    "31" : 257,
    "32" : 266,
    "33" : 228,
    "34" : 227,
    "35" : 234,
    "36" : 257,
    "37" : 241,
    "38" : 216,
    "39" : 242,
    "40" : 212,
    "41" : 212,
    "42" : 210,
    "43" : 191,
    "44" : 233,
    "45" : 199,
    "46" : 182,
    "47" : 213,
    "48" : 187,
    "49" : 202,
    "306" : 1,
    "50" : 160,
    "51" : 148,
    "52" : 170,
    "53" : 130,
    "54" : 162,
    "55" : 128,
    "56" : 142,
    "57" : 144,
    "58" : 139,
    "59" : 130,
    "60" : 117,
    "61" : 118,
    "62" : 102,
    "63" : 114,
    "64" : 102,
    "65" : 111,
    "66" : 102,
    "67" : 103,
    "68" : 105,
    "69" : 82,
    "70" : 89,
    "71" : 79,
    "72" : 85,
    "73" : 80,
    "74" : 66,
    "75" : 51,
    "76" : 100,
    "77" : 67,
    "78" : 60,
    "79" : 64,
    "80" : 67,
    "81" : 62,
    "82" : 46,
    "83" : 52,
    "84" : 51,
    "85" : 52,
    "86" : 51,
    "87" : 42,
    "88" : 39,
    "89" : 59,
    "90" : 43,
    "91" : 45,
    "92" : 42,
    "93" : 35,
    "94" : 30,
    "95" : 32,
    "96" : 28,
    "97" : 36,
    "98" : 37,
    "99" : 23,
    "100" : 34,
    "101" : 44,
    "102" : 36,
    "103" : 23,
    "104" : 28,
    "105" : 23,
    "106" : 27,
    "107" : 26,
    "108" : 23,
    "109" : 25,
    "110" : 27,
    "111" : 32,
    "112" : 19,
    "113" : 13,
    "114" : 21,
    "115" : 23,
    "116" : 19,
    "117" : 20,
    "118" : 19,
    "119" : 15,
    "120" : 16,
    "121" : 12,
    "122" : 12,
    "123" : 12,
    "124" : 10,
    "125" : 9,
    "126" : 11,
    "127" : 12,
    "128" : 9,
    "129" : 11,
    "130" : 13,
    "131" : 15,
    "132" : 6,
    "133" : 5,
    "134" : 6,
    "135" : 6,
    "136" : 11,
    "137" : 5,
    "138" : 5,
    "139" : 10,
    "140" : 4,
    "141" : 2,
    "142" : 9,
    "143" : 11,
    "144" : 5,
    "145" : 4,
    "146" : 8,
    "147" : 4,
    "148" : 4,
    "149" : 5,
    "150" : 7,
    "151" : 5,
    "152" : 4,
    "153" : 5,
    "154" : 5,
    "155" : 4,
    "156" : 6,
    "157" : 2,
    "158" : 6,
    "159" : 2,
    "160" : 2,
    "161" : 3,
    "163" : 4,
    "164" : 3,
    "165" : 2,
    "166" : 3,
    "167" : 2,
    "168" : 1,
    "169" : 3,
    "172" : 2,
    "173" : 2,
    "174" : 1,
    "175" : 2,
    "177" : 1,
    "179" : 1,
    "180" : 2,
    "182" : 1,
    "183" : 1,
    "184" : 2,
    "186" : 1,
    "187" : 1,
    "189" : 2,
    "196" : 3,
    "197" : 3,
    "200" : 1,
    "201" : 1,
    "202" : 2,
    "205" : 2,
    "206" : 2,
    "207" : 1,
    "208" : 1,
    "209" : 1,
    "210" : 2,
    "217" : 2,
    "227" : 2,
    "230" : 1,
    "242" : 1
  },
  "mean" : 50.92829108748978,
  "stdDev" : 28.734154882693392
}