{
  "distribution" : {
    "520" : 1,
    "9" : 1,
    "10" : 1,
    "11" : 4,
    "12" : 4,
    "13" : 9,
    "14" : 13,
    "15" : 14,
    "16" : 24,
    "17" : 33,
    "18" : 47,
    "19" : 48,
    "20" : 53,
    "21" : 67,
    "22" : 89,
    "23" : 85,
    "24" : 106,
    "25" : 105,
    "26" : 148,
    "27" : 149,
    "28" : 153,
    "29" : 157,
    "30" : 149,
    "31" : 175,
    "32" : 147,
    "33" : 156,
    "34" : 184,
    "35" : 200,
    "36" : 193,
    "37" : 181,
    "38" : 186,
    "39" : 191,
    "40" : 177,
    "41" : 189,
    "42" : 227,
    "43" : 195,
    "44" : 198,
    "45" : 207,
    "46" : 192,
    "47" : 199,
    "48" : 174,
    "49" : 180,
    "50" : 175,
    "51" : 195,
    "52" : 170,
    "53" : 158,
    "54" : 148,
    "55" : 165,
    "56" : 156,
    "57" : 167,
    "58" : 160,
    "59" : 153,
    "60" : 159,
    "61" : 158,
    "62" : 152,
    "63" : 149,
    "64" : 110,
    "65" : 144,
    "66" : 121,
    "67" : 127,
    "68" : 132,
    "69" : 112,
    "70" : 119,
    "71" : 123,
    "72" : 100,
    "73" : 102,
    "74" : 100,
    "75" : 98,
    "76" : 89,
    "77" : 91,
    "78" : 91,
    "79" : 82,
    "80" : 112,
    "81" : 77,
    "82" : 77,
    "83" : 87,
    "84" : 69,
    "85" : 93,
    "86" : 62,
    "87" : 79,
    "88" : 80,
    "89" : 81,
    "90" : 60,
    "91" : 71,
    "92" : 66,
    "93" : 70,
    "94" : 60,
    "95" : 51,
    "96" : 45,
    "97" : 63,
    "98" : 49,
    "99" : 57,
    "100" : 60,
    "101" : 39,
    "102" : 47,
    "103" : 56,
    "104" : 49,
    "105" : 43,
    "106" : 46,
    "107" : 31,
    "108" : 40,
    "109" : 40,
    "110" : 49,
    "111" : 36,
    "112" : 42,
    "113" : 48,
    "114" : 35,
    "115" : 44,
    "116" : 29,
    "117" : 29,
    "118" : 39,
    "119" : 40,
    "120" : 22,
    "121" : 31,
    "122" : 24,
    "123" : 35,
    "124" : 22,
    "125" : 23,
    "126" : 39,
    "127" : 27,
    "128" : 19,
    "129" : 19,
    "130" : 25,
    "131" : 24,
    "132" : 23,
    "133" : 19,
    "134" : 19,
    "135" : 21,
    "136" : 16,
    "137" : 25,
    "138" : 14,
    "139" : 13,
    "140" : 10,
    "141" : 21,
    "142" : 15,
    "143" : 19,
    "144" : 18,
    "145" : 8,
    "146" : 15,
    "147" : 16,
    "148" : 19,
    "149" : 8,
    "150" : 8,
    "151" : 10,
    "152" : 8,
    "153" : 10,
    "154" : 10,
    "155" : 5,
    "156" : 9,
    "157" : 15,
    "158" : 4,
    "159" : 12,
    "160" : 5,
    "161" : 9,
    "162" : 4,
    "163" : 12,
    "164" : 8,
    "165" : 10,
    "166" : 11,
    "167" : 12,
    "168" : 10,
    "169" : 16,
    "170" : 9,
    "171" : 5,
    "172" : 6,
    "173" : 7,
    "174" : 11,
    "175" : 5,
    "176" : 8,
    "177" : 6,
    "178" : 9,
    "179" : 6,
    "180" : 3,
    "181" : 9,
    "182" : 4,
    "183" : 6,
    "184" : 4,
    "185" : 6,
    "186" : 5,
    "187" : 7,
    "188" : 8,
    "189" : 10,
    "190" : 1,
    "191" : 1,
    "192" : 7,
    "193" : 3,
    "194" : 4,
    "195" : 5,
    "196" : 2,
    "197" : 2,
    "199" : 6,
    "200" : 3,
    "201" : 2,
    "202" : 2,
    "203" : 4,
    "204" : 1,
    "205" : 3,
    "206" : 5,
    "207" : 3,
    "208" : 2,
    "209" : 2,
    "210" : 4,
    "211" : 2,
    "212" : 1,
    "214" : 2,
    "215" : 1,
    "216" : 2,
    "218" : 3,
    "219" : 1,
    "220" : 3,
    "221" : 1,
    "222" : 1,
    "224" : 3,
    "225" : 1,
    "226" : 2,
    "228" : 1,
    "229" : 1,
    "231" : 2,
    "232" : 2,
    "233" : 2,
    "235" : 1,
    "236" : 1,
    "237" : 2,
    "238" : 1,
    "239" : 1,
    "240" : 1,
    "244" : 1,
    "245" : 1,
    "246" : 1,
    "247" : 1,
    "248" : 1,
    "249" : 1,
    "250" : 1,
    "251" : 2,
    "252" : 1,
    "257" : 1,
    "258" : 1,
    "259" : 1,
    "261" : 1,
    "262" : 1,
    "268" : 1,
    "284" : 1,
    "286" : 1,
    "287" : 1,
    "294" : 1,
    "301" : 1,
    "343" : 1,
    "354" : 1
  },
  "mean" : 65.62246388573284,
  "stdDev" : 37.16536235415152
}